{
  "gitSyncId": "6773c710c83f61054013bc2b_0bcf43a7-88a9-4cd8-a185-0ebd4ada95f5",
  "id": "Registeration_viewFiles.titleDocument",
  "pluginId": "js-plugin",
  "pluginType": "JS",
  "unpublishedAction": {
    "actionConfiguration": {
      "encodeParamsToggle": true,
      "jsArguments": [
        {
          "name": "index"
        }
      ],
      "paginationType": "NONE",
      "timeoutInMillisecond": 10000
    },
    "collectionId": "Registeration_viewFiles",
    "confirmBeforeExecute": false,
    "datasource": {
      "isAutoGenerated": false,
      "name": "UNUSED_DATASOURCE",
      "pluginId": "js-plugin"
    },
    "dynamicBindingPathList": [
      {
        "key": "body"
      }
    ],
    "executeOnLoad": false,
    "fullyQualifiedName": "viewFiles.titleDocument",
    "name": "titleDocument",
    "pageId": "Registeration",
    "userSetOnLoad": false
  }
}