{
  "animateLoading": true,
  "borderRadius": "{{appsmith.theme.borderRadius.appBorderRadius}}",
  "bottomRow": 102,
  "boxShadow": "none",
  "buttonColor": "{{appsmith.theme.colors.primaryColor}}",
  "buttonVariant": "PRIMARY",
  "dynamicBindingPathList": [
    {
      "key": "buttonColor"
    },
    {
      "key": "borderRadius"
    }
  ],
  "dynamicTriggerPathList": [
    {
      "key": "onClick"
    }
  ],
  "iconName": "eye-open",
  "isDisabled": false,
  "isLoading": false,
  "isVisible": true,
  "key": "iujwiwf73f",
  "leftColumn": 40,
  "minWidth": 50,
  "mobileBottomRow": 97,
  "mobileLeftColumn": 45,
  "mobileRightColumn": 49,
  "mobileTopRow": 93,
  "needsErrorInfo": false,
  "onClick": "{{viewProfileDocument.previewAutorizedLetter();}}",
  "parentColumnSpace": 10.40625,
  "parentId": "kwaf34scgz",
  "parentRowSpace": 10,
  "renderMode": "CANVAS",
  "responsiveBehavior": "hug",
  "rightColumn": 44,
  "topRow": 98,
  "type": "ICON_BUTTON_WIDGET",
  "version": 1,
  "widgetId": "sx84ggbu6l",
  "widgetName": "IconButton31Copy"
}